django_import/__init__.py
django_import/admin.py
django_import/apps.py
django_import/config.py
django_import/import_task.py
django_import/models.py
django_import/reflections.py
django_import/reflector.py
django_import/tasks.py
django_import/version.py
django_import/migrations/0001_initial.py
django_import/migrations/__init__.py
django_import-0.0.7.dist-info/LICENSE
django_import-0.0.7.dist-info/METADATA
django_import-0.0.7.dist-info/WHEEL
django_import-0.0.7.dist-info/top_level.txt
django_import-0.0.7.dist-info/RECORD
