Metadata-Version: 2.1
Name: django-import
Version: 0.0.7
Summary: Import to django models
License: LGPL
Keywords: CSV JSON TSV import django fixture
Classifier: Programming Language :: Python
Classifier: Topic :: Software Development :: Libraries :: Python Modules
Classifier: Development Status :: 4 - Beta
Classifier: Framework :: Django
Classifier: Framework :: Django :: 1.10
Classifier: Framework :: Django :: 1.11
Classifier: Framework :: Django :: 2.0
Classifier: Framework :: Django :: 2.1
Classifier: Framework :: Django :: 2.2
Classifier: Framework :: Django :: 3.0
Classifier: Framework :: Django :: 3.1
Classifier: Framework :: Django :: 3.2
Classifier: Framework :: Django :: 4.0
Classifier: Framework :: Django :: 4.1
Classifier: Programming Language :: Python :: 2.7
Classifier: Programming Language :: Python :: 3.6
Classifier: Programming Language :: Python :: 3.7
Classifier: Programming Language :: Python :: 3.8
Classifier: Programming Language :: Python :: 3.9
Classifier: Programming Language :: Python :: 3.10
Classifier: Programming Language :: Python :: 3.11
Classifier: License :: OSI Approved :: GNU Library or Lesser General Public License (LGPL)
License-File: LICENSE
Requires-Dist: django
Requires-Dist: pandas
Requires-Dist: django-jsoneditor
Requires-Dist: django-extensions
Requires-Dist: markdown
Requires-Dist: six
Requires-Dist: openpyxl
Requires-Dist: xlrd (>=1.0.0)
